IXBrokerCustomer_pb2.py
Burger_pb2.py
Pasta_pb2.py
IXBrokerCustomer_pb2_grpc.py
Pasta_pb2_grpc.py
Burger_pb2_grpc.py
Pizza_pb2_grpc.py
Pizza_pb2.py
ixbrokercustomer-0.0.3.dist-info/WHEEL
ixbrokercustomer-0.0.3.dist-info/METADATA
ixbrokercustomer-0.0.3.dist-info/RECORD