Metadata-Version: 2.1
Name: ixbrokercustomer
Version: 0.0.3
Summary: Auto-generated python gRPC stubs for communication between broker and customer applications
Requires-Python: >=3.7
Requires-Dist: grpcio
Requires-Dist: protobuf
